LICENSE
MANIFEST.in
README.md
requirements.txt
setup.py
abem/__init__.py
abem.egg-info/PKG-INFO
abem.egg-info/SOURCES.txt
abem.egg-info/dependency_links.txt
abem.egg-info/not-zip-safe
abem.egg-info/requires.txt
abem.egg-info/top_level.txt
iops_cpp/helmholtz_integrals.cpp
iops_cpp/helmholtz_integrals.pyx
iops_cpp/iops_cpp.cpp
iops_cpp/iops_cpp.h
iops_cpp/iops_cpp.pxd
iops_sci/__init__.py
iops_sci/iops_sci.py
notebooks/exterior_helmholtz_solver_2d.ipynb
notebooks/exterior_helmholtz_solver_3d.ipynb
notebooks/exterior_helmholtz_solver_rad.ipynb
notebooks/interior_helmholtz_solver_2d.ipynb
notebooks/interior_helmholtz_solver_3d.ipynb
notebooks/interior_helmholtz_solver_rad.ipynb
notebooks/rayleigh_cavity_1.ipynb
notebooks/rayleigh_cavity_2.ipynb
notebooks/rayleigh_solver_3d_disk.ipynb
notebooks/rayleigh_solver_square.ipynb
src/acoustic_boundaries.c
src/acoustic_boundaries.pyx
src/acoustic_properties.c
src/acoustic_properties.pyx
src/helmholtz_solvers.c
src/helmholtz_solvers.pyx
src/iops_pyx.c
src/iops_pyx.pyx
src/rayleigh_solvers.c
src/rayleigh_solvers.pyx
src/solver.c
src/solver.pyx