Metadata-Version: 2.1
Name: abem
Version: 0.2b2
Summary: Boundary Element Method for Acoustic Simulations
Home-page: http://github.com/fjargsto/abem
Author: Frank Jargstorff
License: GNU General Public License
Download-URL: https://github.com/fjargsto/abem/archive/abem-0.2a2.tar.gz
Platform: UNKNOWN
